execredis/__init__.py
execredis/connection.py
execredis/handler.py
exec_redis-0.0.20.dist-info/LICENSE
exec_redis-0.0.20.dist-info/METADATA
exec_redis-0.0.20.dist-info/WHEEL
exec_redis-0.0.20.dist-info/top_level.txt
exec_redis-0.0.20.dist-info/RECORD
