Metadata-Version: 2.1
Name: exec-redis
Version: 0.0.20
Summary: Redis handler.
Home-page: https://github.com/Supplayer/exec_redis.git
Author: Supplayer
Author-email: x254724521@hotmail.com
License: UNKNOWN
Platform: UNKNOWN
Classifier: Programming Language :: Python :: 3
Classifier: License :: OSI Approved :: MIT License
Classifier: Operating System :: OS Independent
Requires-Python: >=3.6
License-File: LICENSE
Requires-Dist: redis
Requires-Dist: redis-py-cluster
